MANIFEST.in
README.rst
license.txt
setup.py
jenkinsreport/__init__.py
jenkinsreport/command_line.py
jenkinsreport/results.py
jenkinsreport.egg-info/PKG-INFO
jenkinsreport.egg-info/SOURCES.txt
jenkinsreport.egg-info/dependency_links.txt
jenkinsreport.egg-info/entry_points.txt
jenkinsreport.egg-info/not-zip-safe
jenkinsreport.egg-info/requires.txt
jenkinsreport.egg-info/top_level.txt