Metadata-Version: 1.0
Name: jenkinsreport
Version: 0.1.0
Summary: Tools for reporting Jenkins test results information
Home-page: http://github.com/sachu/jenkinsreport
Author: Stephen Chu
Author-email: chu.stephen@gmail.com
License: MIT
Platform: UNKNOWN
